pdfuris/__init__.py
pdfuris/__main__.py
pdfuris/py.typed
pdfuris-0.1.dist-info/METADATA
pdfuris-0.1.dist-info/WHEEL
pdfuris-0.1.dist-info/entry_points.txt
pdfuris-0.1.dist-info/top_level.txt
pdfuris-0.1.dist-info/RECORD
